lizi_engine/__init__.py
lizi_engine/compute/__init__.py
lizi_engine/compute/cpu_vector_field.py
lizi_engine/compute/gpu_vector_field.py
lizi_engine/compute/vector_field.py
lizi_engine/core/__init__.py
lizi_engine/core/app.py
lizi_engine/core/config.py
lizi_engine/core/container.py
lizi_engine/core/events.py
lizi_engine/core/state.py
lizi_engine/graphics/__init__.py
lizi_engine/graphics/renderer.py
lizi_engine/input/__init__.py
lizi_engine/input/input_handler.py
lizi_engine/input/key_map.py
lizi_engine/input/mouse_map.py
lizi_engine/window/__init__.py
lizi_engine/window/window.py
lizi_engine-0.1.10.dist-info/licenses/LICENSE
lizi_engine-0.1.10.dist-info/METADATA
lizi_engine-0.1.10.dist-info/WHEEL
lizi_engine-0.1.10.dist-info/top_level.txt
lizi_engine-0.1.10.dist-info/RECORD
