Metadata-Version: 2.4
Name: lizi-engine
Version: 0.1.10
Summary: LiziEngine
Author: 是雫雫酱呦
License: MIT
Classifier: Programming Language :: Python :: 3
Classifier: License :: OSI Approved :: MIT License
Classifier: Operating System :: OS Independent
Requires-Python: >=3.8
License-File: LICENSE
Requires-Dist: numpy>=1.21.0
Requires-Dist: glfw>=2.5.0
Requires-Dist: PyOpenGL>=3.1.6
Requires-Dist: pyopencl>=2021.1.0
Requires-Dist: pybind11>=2.6.0
Dynamic: license-file
